gsheetsdb/__init__.py
gsheetsdb/__version__.py
gsheetsdb/auth.py
gsheetsdb/console.py
gsheetsdb/convert.py
gsheetsdb/db.py
gsheetsdb/dialect.py
gsheetsdb/exceptions.py
gsheetsdb/formatting.py
gsheetsdb/processors.py
gsheetsdb/query.py
gsheetsdb/sqlite.py
gsheetsdb/translator.py
gsheetsdb/types.py
gsheetsdb/url.py
gsheetsdb/utils.py
gsheetsdb-0.1.13.dist-info/LICENSE
gsheetsdb-0.1.13.dist-info/METADATA
gsheetsdb-0.1.13.dist-info/WHEEL
gsheetsdb-0.1.13.dist-info/entry_points.txt
gsheetsdb-0.1.13.dist-info/top_level.txt
gsheetsdb-0.1.13.dist-info/RECORD
