Metadata-Version: 2.1
Name: gsheetsdb
Version: 0.1.13
Summary: Python DB-API and SQLAlchemy interface for Google Spreadsheets.
Home-page: https://github.com/betodealmeida/gsheets-db-api
Author: Beto Dealmeida
Author-email: beto@dealmeida.net
License: MIT
Platform: UNKNOWN
Classifier: License :: OSI Approved :: MIT License
Classifier: Programming Language :: Python
Classifier: Programming Language :: Python :: 3.4
Classifier: Programming Language :: Python :: 3.5
Classifier: Programming Language :: Python :: 3.6
Classifier: Programming Language :: Python :: 3.7
Classifier: Programming Language :: Python :: Implementation :: CPython
Classifier: Programming Language :: Python :: Implementation :: PyPy
Provides-Extra: dev
Provides-Extra: sqlalchemy
Provides-Extra: cli
